invenio_oarepo_invenio_model/__init__.py
invenio_oarepo_invenio_model/version.py
invenio_oarepo_invenio_model/included_mappings/v6/invenio-v1.0.0.json
invenio_oarepo_invenio_model/included_mappings/v7/invenio-v1.0.0.json
invenio_oarepo_invenio_model/jsonschemas/__init__.py
invenio_oarepo_invenio_model/jsonschemas/invenio-v1.0.0.json
invenio_oarepo_invenio_model/marshmallow/__init__.py
invenio_oarepo_invenio_model-2.0.0.dist-info/LICENSE
invenio_oarepo_invenio_model-2.0.0.dist-info/METADATA
invenio_oarepo_invenio_model-2.0.0.dist-info/WHEEL
invenio_oarepo_invenio_model-2.0.0.dist-info/entry_points.txt
invenio_oarepo_invenio_model-2.0.0.dist-info/top_level.txt
invenio_oarepo_invenio_model-2.0.0.dist-info/RECORD
