Metadata-Version: 2.1
Name: invenio-oarepo-invenio-model
Version: 2.0.0
Summary: Invenio data model for OARepo
Home-page: https://github.com/oarepo/invenio_oarepo_invenio_model
Author: Miroslav Simek
Author-email: miroslav.simek@vscht.cz
License: MIT
Platform: any
Classifier: Environment :: Web Environment
Classifier: Intended Audience :: Developers
Classifier: License :: OSI Approved :: MIT License
Classifier: Operating System :: OS Independent
Classifier: Programming Language :: Python
Classifier: Topic :: Internet :: WWW/HTTP :: Dynamic Content
Classifier: Topic :: Software Development :: Libraries :: Python Modules
Classifier: Programming Language :: Python :: 2
Classifier: Programming Language :: Python :: 2.7
Classifier: Programming Language :: Python :: 3
Classifier: Programming Language :: Python :: 3.5
Classifier: Development Status :: 4 - Beta
Provides-Extra: tests
Requires-Dist: pytest (>=4.6.3) ; extra == 'tests'
Requires-Dist: oarepo[tests] (~=3.1.1) ; extra == 'tests'
Provides-Extra: tests-es7
Requires-Dist: pytest (>=4.6.3) ; extra == 'tests-es7'
Requires-Dist: oarepo[tests-es7] (~=3.1.1) ; extra == 'tests-es7'
